thonnycontrib/ThonnyLogsGenerator.py
thonnycontrib/__init__.py
thonnycontrib/environement_vars.py
thonnycontrib/exceptions.py
thonnycontrib/plugin_loader.py
thonnycontrib/properties.py
thonnycontrib/utils.py
thonnycontrib/backend/__init__.py
thonnycontrib/backend/ast_parser.py
thonnycontrib/backend/doctest_parser.py
thonnycontrib/backend/evaluator.py
thonnycontrib/backend/l1test_backend.py
thonnycontrib/backend/test_finder.py
thonnycontrib/backend/verdicts/ExampleVerdict.py
thonnycontrib/backend/verdicts/ExceptionVerdict.py
thonnycontrib/backend/verdicts/FailedVerdict.py
thonnycontrib/backend/verdicts/FailedWhenExceptionExpectedVerdict.py
thonnycontrib/backend/verdicts/PassedVerdict.py
thonnycontrib/backend/verdicts/SetupVerdict.py
thonnycontrib/backend/verdicts/__init__.py
thonnycontrib/docs/__init__.py
thonnycontrib/docs/res/error_icon.png
thonnycontrib/docs/res/failed.png
thonnycontrib/docs/res/l1test_debug.png
thonnycontrib/docs/res/l1test_icon.png
thonnycontrib/docs/res/l1test_icon_old.png
thonnycontrib/docs/res/outline_class.png
thonnycontrib/docs/res/outline_method.gif
thonnycontrib/docs/res/passed.png
thonnycontrib/docs/res/pending_icon.png
thonnycontrib/docs/res/restart_icon.png
thonnycontrib/docs/res/test_only_btn.png
thonnycontrib/docs/res/warning.png
thonnycontrib/docstring_generator/__init__.py
thonnycontrib/docstring_generator/doc_generator.py
thonnycontrib/docstring_generator/doc_template.py
thonnycontrib/l1test_configuration/__init__.py
thonnycontrib/l1test_configuration/l1test_options.py
thonnycontrib/l1test_frontend/__init__.py
thonnycontrib/l1test_frontend/l1test_error_view.py
thonnycontrib/l1test_frontend/l1test_reporter.py
thonnycontrib/l1test_frontend/l1test_runner.py
thonnycontrib/l1test_frontend/l1test_treeview.py
thonnycontrib/l1test_frontend/outlines.py
thonnycontrib/tests/__init__.py
thonnycontrib/tests/backend_mock.py
thonnycontrib/tests/test_doc_generator.py
thonnycontrib/tests/tests_example_no_expected.py
UpyTest-3.1.7.dist-info/METADATA
UpyTest-3.1.7.dist-info/WHEEL
UpyTest-3.1.7.dist-info/top_level.txt
UpyTest-3.1.7.dist-info/RECORD
