Metadata-Version: 2.1
Name: UpyTest
Version: 3.1.7
Summary: A plug-in which adds a test framework
Home-page: https://gitlab.univ-lille.fr/reda.idtaleb.etu/thonny_test_framework
Author: Réda Id-taleb
Platform: Windows
Platform: macOS
Platform: Linux
Classifier: Topic :: Education :: Testing
Classifier: Programming Language :: Python :: 3
Classifier: License :: OSI Approved :: MIT License
Classifier: Operating System :: OS Independent
Classifier: Development Status :: 3 - Alpha
Classifier: Intended Audience :: Education
Requires-Python: >=3.9
Requires-Dist: thonny (>=4.0.0)
